simbio/models/corbat2018/__init__.py
simbio_corbat2018-0.1.0.dist-info/LICENSE
simbio_corbat2018-0.1.0.dist-info/METADATA
simbio_corbat2018-0.1.0.dist-info/WHEEL
simbio_corbat2018-0.1.0.dist-info/top_level.txt
simbio_corbat2018-0.1.0.dist-info/RECORD
